plateparser/__init__.py
plateparser/parser.py
plateparser-0.1.0.dist-info/LICENSE
plateparser-0.1.0.dist-info/METADATA
plateparser-0.1.0.dist-info/WHEEL
plateparser-0.1.0.dist-info/top_level.txt
plateparser-0.1.0.dist-info/RECORD
